{
  "total_figures": 215,
  "resolved_local": 105,
  "resolved_external": 0,
  "needs_external": 110,
  "summary": {
    "fully_processed": 105,
    "pending_external": 110,
    "percent_complete": 48.8
  },
  "figures": {
    "resolved_local": [
      {
        "id": "fig_0001",
        "classification": "logo",
        "description": "The image features the logo of Texas Instruments (TI), a company that specializes in electronic products and technology."
      },
      {
        "id": "fig_0003",
        "classification": "logo",
        "description": "The image features a black and white triangle-shaped logo with two weights, one on each side of the triangle. The weight"
      },
      {
        "id": "fig_0004",
        "classification": "logo",
        "description": "The image presents two electronic components, a larger component and a smaller one, both featuring the logo of the state"
      },
      {
        "id": "fig_0005",
        "classification": "screenshot",
        "description": "The image shows a close-up view of three black and white numbers, each with the same length - 5 digits long. The first n"
      },
      {
        "id": "fig_0006",
        "classification": "logo",
        "description": "The image features a striking black and white logo for a company, which is composed of three triangles arranged in a tri"
      },
      {
        "id": "fig_0007",
        "classification": "logo",
        "description": "The image features the logo of Texas Instruments (TI), a company that specializes in electronic products and technology."
      },
      {
        "id": "fig_0008",
        "classification": "logo",
        "description": "The image features the logo of Texas Instruments (TI), a company that specializes in electronic products and technology."
      },
      {
        "id": "fig_0009",
        "classification": "logo",
        "description": "The image features the logo of Texas Instruments (TI), a company that specializes in electronic products and technology."
      },
      {
        "id": "fig_0010",
        "classification": "logo",
        "description": "The image features the logo of Texas Instruments (TI), a company that specializes in electronic products and technology."
      },
      {
        "id": "fig_0013",
        "classification": "other",
        "description": "The image shows a close-up view of three black and white license plates, each with the number \"DAC\" written in capital l"
      },
      {
        "id": "fig_0014",
        "classification": "icon",
        "description": "The image presents a detailed black and white diagram of an electronic circuit, specifically focusing on the components "
      },
      {
        "id": "fig_0015",
        "classification": "logo",
        "description": "The image features the logo of Texas Instruments (TI), a company that specializes in electronic products and technology."
      },
      {
        "id": "fig_0016",
        "classification": "logo",
        "description": "The image features the logo of Texas Instruments (TI), a company that specializes in electronic products and technology."
      },
      {
        "id": "fig_0023",
        "classification": "other",
        "description": "The image shows a close-up view of three black and white license plates, each with the number \"DAC\" written in capital l"
      },
      {
        "id": "fig_0024",
        "classification": "other",
        "description": "The image shows a close-up view of three black and white license plates, each with the number \"DAC\" printed on them in a"
      },
      {
        "id": "fig_0025",
        "classification": "logo",
        "description": "The image features the logo of Texas Instruments (TI), a company that specializes in electronic products and technology."
      },
      {
        "id": "fig_0032",
        "classification": "logo",
        "description": "The image features the logo of Texas Instruments (TI), a company that specializes in electronic products and technology."
      },
      {
        "id": "fig_0033",
        "classification": "other",
        "description": "The image shows a close-up view of three black and white license plates, each with the number \"DAC\" written in capital l"
      },
      {
        "id": "fig_0040",
        "classification": "other",
        "description": "The image shows a close-up view of three black and white license plates, each with the number \"DAC\" printed on them in a"
      },
      {
        "id": "fig_0041",
        "classification": "logo",
        "description": "The image features the logo of Texas Instruments (TI), a company that specializes in electronic products and technology."
      },
      {
        "id": "fig_0043",
        "classification": "logo",
        "description": "The image features the logo of Texas Instruments (TI), a company that specializes in electronic products and technology."
      },
      {
        "id": "fig_0044",
        "classification": "other",
        "description": "The image shows a close-up view of three black and white license plates, each with the number \"DAC\" written in capital l"
      },
      {
        "id": "fig_0050",
        "classification": "other",
        "description": "The image shows a close-up view of three black and white license plates, each with the number \"DAC\" printed on them in a"
      },
      {
        "id": "fig_0051",
        "classification": "logo",
        "description": "The image features the logo of Texas Instruments (TI), a company that specializes in electronic products and technology."
      },
      {
        "id": "fig_0058",
        "classification": "logo",
        "description": "The image features the logo of Texas Instruments (TI), a company that specializes in electronic products and technology."
      },
      {
        "id": "fig_0059",
        "classification": "other",
        "description": "The image shows a close-up view of three black and white license plates, each with the number \"DAC\" written in capital l"
      },
      {
        "id": "fig_0065",
        "classification": "screenshot",
        "description": "The image presents a black and white diagram that illustrates the relationship between falling edge, trigger pulse, and "
      },
      {
        "id": "fig_0066",
        "classification": "other",
        "description": "The image shows a close-up view of three black and white license plates, each with the number \"DAC\" printed on them in a"
      },
      {
        "id": "fig_0067",
        "classification": "logo",
        "description": "The image features the logo of Texas Instruments (TI), a company that specializes in electronic products and technology."
      },
      {
        "id": "fig_0073",
        "classification": "icon",
        "description": "The image presents a black and white diagram that illustrates the power-off glitch of a DAC (Digital Audio Coder) amplif"
      },
      {
        "id": "fig_0074",
        "classification": "logo",
        "description": "The image features the logo of Texas Instruments (TI), a company that specializes in electronic products and technology."
      },
      {
        "id": "fig_0075",
        "classification": "other",
        "description": "The image shows a close-up view of three black and white license plates, each with the number \"DAC\" written in capital l"
      },
      {
        "id": "fig_0077",
        "classification": "screenshot",
        "description": "The image presents a detailed electronic datasheet for a device that measures the trigger pulse of a signal. The device "
      },
      {
        "id": "fig_0080",
        "classification": "screenshot",
        "description": "The image presents a detailed electronic datasheet, likely for a device or component that measures the trigger pulse of "
      },
      {
        "id": "fig_0082",
        "classification": "other",
        "description": "The image shows a close-up view of three black and white license plates, each with the number \"DAC\" printed on them in a"
      },
      {
        "id": "fig_0083",
        "classification": "logo",
        "description": "The image features the logo of Texas Instruments (TI), a company that specializes in electronic products and technology."
      },
      {
        "id": "fig_0086",
        "classification": "logo",
        "description": "The image features the logo of Texas Instruments (TI), a company that specializes in electronic products and technology."
      },
      {
        "id": "fig_0090",
        "classification": "other",
        "description": "The image shows a close-up view of three black and white license plates, each with the number \"DAC\" written in capital l"
      },
      {
        "id": "fig_0091",
        "classification": "other",
        "description": "The image shows a close-up view of three black and white license plates, each with the number \"DAC\" printed on them in a"
      },
      {
        "id": "fig_0098",
        "classification": "logo",
        "description": "The image features the logo of Texas Instruments (TI), a company that specializes in electronic products and technology."
      },
      {
        "id": "fig_0099",
        "classification": "logo",
        "description": "The image features the logo of Texas Instruments (TI), a company that specializes in electronic products and technology."
      },
      {
        "id": "fig_0100",
        "classification": "other",
        "description": "The image shows a close-up view of three black and white license plates, each with the number \"DAC\" written in capital l"
      },
      {
        "id": "fig_0107",
        "classification": "logo",
        "description": "The image features the logo of Texas Instruments (TI), a company that specializes in electronic products and technology."
      },
      {
        "id": "fig_0114",
        "classification": "logo",
        "description": "The image features the logo of Texas Instruments (TI), a company that specializes in electronic products and technology."
      },
      {
        "id": "fig_0115",
        "classification": "other",
        "description": "The image shows a close-up view of three black and white license plates, each with the number \"DAC\" written in capital l"
      },
      {
        "id": "fig_0122",
        "classification": "other",
        "description": "The image shows a close-up view of three black and white license plates, each with the number \"DAC\" printed on them in a"
      },
      {
        "id": "fig_0123",
        "classification": "logo",
        "description": "The image features the logo of Texas Instruments (TI), a company that specializes in electronic products and technology."
      },
      {
        "id": "fig_0129",
        "classification": "logo",
        "description": "The image features the logo of Texas Instruments (TI), a company that specializes in electronic products and technology."
      },
      {
        "id": "fig_0130",
        "classification": "other",
        "description": "The image shows a close-up view of three black and white license plates, each with the number \"DAC\" written in capital l"
      },
      {
        "id": "fig_0137",
        "classification": "other",
        "description": "The image shows a close-up view of three black and white license plates, each with the number \"DAC\" printed on them in a"
      },
      {
        "id": "fig_0138",
        "classification": "logo",
        "description": "The image features the logo of Texas Instruments (TI), a company that specializes in electronic products and technology."
      },
      {
        "id": "fig_0145",
        "classification": "logo",
        "description": "The image features the logo of Texas Instruments (TI), a company that specializes in electronic products and technology."
      },
      {
        "id": "fig_0146",
        "classification": "other",
        "description": "The image shows a close-up view of three black and white license plates, each with the number \"DAC\" written in capital l"
      },
      {
        "id": "fig_0152",
        "classification": "icon",
        "description": "The image presents a black and white diagram that illustrates the relationship between external reference, voltage, and "
      },
      {
        "id": "fig_0153",
        "classification": "logo",
        "description": "The image features the logo of Texas Instruments (TI), a company that specializes in electronic products and technology."
      },
      {
        "id": "fig_0156",
        "classification": "screenshot",
        "description": "The image presents a detailed electronic datasheet for an external reference device, specifically designed to measure th"
      },
      {
        "id": "fig_0158",
        "classification": "logo",
        "description": "The image features the logo of Texas Instruments (TI), a company that specializes in electronic products and technology."
      },
      {
        "id": "fig_0159",
        "classification": "other",
        "description": "The image presents a black and white diagram of an electronic circuit, likely used for a DAC (Digital Amplifier Controll"
      },
      {
        "id": "fig_0161",
        "classification": "other",
        "description": "The image shows a close-up view of three black and white license plates, each with the number \"DAC\" written in capital l"
      },
      {
        "id": "fig_0162",
        "classification": "icon",
        "description": "The image presents a detailed black and white diagram of an electronic circuit, specifically focusing on the components "
      },
      {
        "id": "fig_0163",
        "classification": "logo",
        "description": "The image features the logo of Texas Instruments (TI), a company that specializes in electronic products and technology."
      },
      {
        "id": "fig_0164",
        "classification": "icon",
        "description": "The image presents a detailed diagram of a digital circuit, specifically focusing on the input and output components. Th"
      },
      {
        "id": "fig_0165",
        "classification": "logo",
        "description": "The image features the logo of Texas Instruments (TI), a company that specializes in electronic products and technology."
      },
      {
        "id": "fig_0166",
        "classification": "icon",
        "description": "The image presents a detailed diagram of a data line stable (DSL) circuit, with the components clearly labeled and organ"
      },
      {
        "id": "fig_0167",
        "classification": "logo",
        "description": "The image features the logo of Texas Instruments (TI), a company that specializes in electronic products and technology."
      },
      {
        "id": "fig_0168",
        "classification": "icon",
        "description": "The image presents a detailed diagram of a digital circuit, specifically focusing on the clock line and its relationship"
      },
      {
        "id": "fig_0169",
        "classification": "logo",
        "description": "The image features the logo of Texas Instruments (TI), a company that specializes in electronic products and technology."
      },
      {
        "id": "fig_0170",
        "classification": "logo",
        "description": "The image features the logo of Texas Instruments (TI), a company that specializes in electronic products and technology."
      },
      {
        "id": "fig_0171",
        "classification": "logo",
        "description": "The image features the logo of Texas Instruments (TI), a company that specializes in electronic products and technology."
      },
      {
        "id": "fig_0172",
        "classification": "logo",
        "description": "The image features the logo of Texas Instruments (TI), a company that specializes in electronic products and technology."
      },
      {
        "id": "fig_0173",
        "classification": "logo",
        "description": "The image features the logo of Texas Instruments (TI), a company that specializes in electronic products and technology."
      },
      {
        "id": "fig_0174",
        "classification": "logo",
        "description": "The image features the logo of Texas Instruments (TI), a company that specializes in electronic products and technology."
      },
      {
        "id": "fig_0175",
        "classification": "logo",
        "description": "The image features the logo of Texas Instruments (TI), a company that specializes in electronic products and technology."
      },
      {
        "id": "fig_0176",
        "classification": "logo",
        "description": "The image features the logo of Texas Instruments (TI), a company that specializes in electronic products and technology."
      },
      {
        "id": "fig_0177",
        "classification": "logo",
        "description": "The image features the logo of Texas Instruments (TI), a company that specializes in electronic products and technology."
      },
      {
        "id": "fig_0178",
        "classification": "icon",
        "description": "The image presents a black and white diagram of an electronic circuit, specifically focusing on the components involved "
      },
      {
        "id": "fig_0179",
        "classification": "logo",
        "description": "The image features the logo of Texas Instruments (TI), a company that specializes in electronic products and technology."
      },
      {
        "id": "fig_0180",
        "classification": "logo",
        "description": "The image features the logo of Texas Instruments (TI), a company that specializes in electronic products and technology."
      },
      {
        "id": "fig_0183",
        "classification": "other",
        "description": "The image shows a close-up view of three black and white license plates, each with the number \"DAC\" written in capital l"
      },
      {
        "id": "fig_0184",
        "classification": "logo",
        "description": "The image features the logo of Texas Instruments (TI), a company that specializes in electronic products and technology."
      },
      {
        "id": "fig_0186",
        "classification": "logo",
        "description": "The image features the logo of Texas Instruments (TI), a company that specializes in electronic products and technology."
      },
      {
        "id": "fig_0187",
        "classification": "logo",
        "description": "The image features the logo of Texas Instruments (TI), a company that specializes in electronic products and technology."
      },
      {
        "id": "fig_0188",
        "classification": "logo",
        "description": "The image features the logo of Texas Instruments (TI), a company that specializes in electronic products and technology."
      },
      {
        "id": "fig_0189",
        "classification": "other",
        "description": "The image shows a close-up view of three black and white license plates, each with the number \"DAC\" printed on them in a"
      },
      {
        "id": "fig_0190",
        "classification": "logo",
        "description": "The image features the logo of Texas Instruments (TI), a company that specializes in electronic products and technology."
      },
      {
        "id": "fig_0191",
        "classification": "logo",
        "description": "The image features the logo of Texas Instruments (TI), a company that specializes in electronic products and technology."
      },
      {
        "id": "fig_0192",
        "classification": "logo",
        "description": "The image features the logo of Texas Instruments (TI), a company that specializes in electronic products and technology."
      },
      {
        "id": "fig_0193",
        "classification": "logo",
        "description": "The image features the logo of Texas Instruments (TI), a company that specializes in electronic products and technology."
      },
      {
        "id": "fig_0194",
        "classification": "logo",
        "description": "The image features the logo of Texas Instruments (TI), a company that specializes in electronic products and technology."
      },
      {
        "id": "fig_0195",
        "classification": "screenshot",
        "description": "The image presents a detailed technical drawing of a circular device, likely a part or component of a larger electronic "
      },
      {
        "id": "fig_0196",
        "classification": "icon",
        "description": "The image presents a detailed diagram of a sprockets pocket quadrant, which is a component used in electronic devices to"
      },
      {
        "id": "fig_0197",
        "classification": "logo",
        "description": "The image features the logo of Texas Instruments (TI), a company that specializes in electronic products and technology."
      },
      {
        "id": "fig_0198",
        "classification": "photo",
        "description": "The image presents a black and white diagram of a cardboard box with its lid open, revealing the interior. The box is ou"
      },
      {
        "id": "fig_0199",
        "classification": "logo",
        "description": "The image features the logo of Texas Instruments (TI), a company that specializes in electronic products and technology."
      },
      {
        "id": "fig_0200",
        "classification": "mechanical",
        "description": "The image presents a detailed diagram of a tube with measurements and specifications for its dimensions, including the l"
      },
      {
        "id": "fig_0201",
        "classification": "icon",
        "description": "The image presents a black and white electronic device, possibly a semiconductor chip or a component of a larger circuit"
      },
      {
        "id": "fig_0202",
        "classification": "logo",
        "description": "The image features the logo of Texas Instruments (TI), a company that specializes in electronic products and technology."
      },
      {
        "id": "fig_0204",
        "classification": "logo",
        "description": "The image features a black and white logo for Texas Instruments (TI). The logo is prominently displayed in the center of"
      },
      {
        "id": "fig_0206",
        "classification": "logo",
        "description": "The image features a black and white logo for Texas Instruments (TI). The logo is prominently displayed in the center of"
      },
      {
        "id": "fig_0208",
        "classification": "logo",
        "description": "The image features a black and white logo for Texas Instruments (TI). The logo is prominently displayed in the center of"
      },
      {
        "id": "fig_0210",
        "classification": "logo",
        "description": "The image features a logo for Texas Instruments (TI) that is predominantly black and white in color, with the company's "
      },
      {
        "id": "fig_0212",
        "classification": "screenshot",
        "description": "The image presents a detailed technical drawing of a soldering mask, which is a crucial tool in the field of electronics"
      },
      {
        "id": "fig_0213",
        "classification": "logo",
        "description": "The image features a logo for Texas Instruments (TI) that is predominantly black and white in color, with the company's "
      },
      {
        "id": "fig_0214",
        "classification": "screenshot",
        "description": "The image presents a detailed technical drawing of a soldering iron, with the focus on its components and their dimensio"
      },
      {
        "id": "fig_0215",
        "classification": "logo",
        "description": "The image features the logo of Texas Instruments (TI), a company that specializes in electronic products and technology."
      }
    ],
    "needs_external": [
      {
        "id": "fig_0002",
        "image_path": "out/dac5578/figures/fig_0002.png",
        "classification": "register_map",
        "description": "The image presents a detailed black and white diagram of a digital circuit board, specifically focusing on the DAC5728 c"
      },
      {
        "id": "fig_0011",
        "image_path": "out/dac5578/figures/fig_0011.png",
        "classification": "block_diagram",
        "description": "The image presents a detailed diagram of a digital circuit board, specifically focusing on the DACX5728 device. The DACX"
      },
      {
        "id": "fig_0012",
        "image_path": "out/dac5578/figures/fig_0012.png",
        "classification": "block_diagram",
        "description": "The image presents a detailed diagram of a circuit board, specifically focusing on the DACX5828 chip. The DACX5828 is a "
      },
      {
        "id": "fig_0017",
        "image_path": "out/dac5578/figures/fig_0017.png",
        "classification": "plot",
        "description": "The image presents a graph that displays the relationship between linearity error and digital input code (DAC) for eight"
      },
      {
        "id": "fig_0018",
        "image_path": "out/dac5578/figures/fig_0018.png",
        "classification": "plot",
        "description": "The image presents a graph with the x-axis labeled \"Digital input code\" and the y-axis labeled \"Linearity error\". The gr"
      },
      {
        "id": "fig_0019",
        "image_path": "out/dac5578/figures/fig_0019.png",
        "classification": "plot",
        "description": "The image presents a graph with the x-axis labeled \"Digital input code\" and the y-axis labeled \"Linear error\". The graph"
      },
      {
        "id": "fig_0020",
        "image_path": "out/dac5578/figures/fig_0020.png",
        "classification": "plot",
        "description": "The image presents a graph with the x-axis labeled \"Digital input code\" and the y-axis labeled \"Differential linearity e"
      },
      {
        "id": "fig_0021",
        "image_path": "out/dac5578/figures/fig_0021.png",
        "classification": "plot",
        "description": "The image presents a graph with the x-axis labeled \"Digital input code\" and the y-axis labeled \"Differential linearity e"
      },
      {
        "id": "fig_0022",
        "image_path": "out/dac5578/figures/fig_0022.png",
        "classification": "plot",
        "description": "The image presents a graph with two lines, one representing the digital input code and the other showing the differentia"
      },
      {
        "id": "fig_0026",
        "image_path": "out/dac5578/figures/fig_0026.png",
        "classification": "plot",
        "description": "The image presents a line graph that displays the relationship between digital input code (DAC) and linear error. The x-"
      },
      {
        "id": "fig_0027",
        "image_path": "out/dac5578/figures/fig_0027.png",
        "classification": "plot",
        "description": "The image presents a graph that displays the relationship between linearity error and digital input code (DAC) for vario"
      },
      {
        "id": "fig_0028",
        "image_path": "out/dac5578/figures/fig_0028.png",
        "classification": "pinout",
        "description": "The image presents a graph with the x-axis labeled \"Digital input code\" and the y-axis labeled \"Linearity error\". The gr"
      },
      {
        "id": "fig_0029",
        "image_path": "out/dac5578/figures/fig_0029.png",
        "classification": "plot",
        "description": "The image presents a graph with two lines, one representing the differential linearity error and the other representing "
      },
      {
        "id": "fig_0030",
        "image_path": "out/dac5578/figures/fig_0030.png",
        "classification": "plot",
        "description": "The image presents a graph with the x-axis labeled \"Digital input code\" and the y-axis labeled \"Differential linearity e"
      },
      {
        "id": "fig_0031",
        "image_path": "out/dac5578/figures/fig_0031.png",
        "classification": "plot",
        "description": "The image presents a graph with two lines, one representing the differential linearity error and the other showing the d"
      },
      {
        "id": "fig_0034",
        "image_path": "out/dac5578/figures/fig_0034.png",
        "classification": "plot",
        "description": "The image presents a graph with the x-axis labeled \"Digital input code\" and the y-axis labeled \"Linearity error\". The gr"
      },
      {
        "id": "fig_0035",
        "image_path": "out/dac5578/figures/fig_0035.png",
        "classification": "plot",
        "description": "The image presents a graph with the x-axis labeled \"Digital input code\" and the y-axis labeled \"Linearity error\". The gr"
      },
      {
        "id": "fig_0036",
        "image_path": "out/dac5578/figures/fig_0036.png",
        "classification": "plot",
        "description": "The image presents a graph with the x-axis labeled \"Digital input code\" and the y-axis labeled \"Linearity error\". The gr"
      },
      {
        "id": "fig_0037",
        "image_path": "out/dac5578/figures/fig_0037.png",
        "classification": "plot",
        "description": "The image presents a graph with the x-axis labeled \"Digital input code\" and the y-axis labeled \"Differential linearity e"
      },
      {
        "id": "fig_0038",
        "image_path": "out/dac5578/figures/fig_0038.png",
        "classification": "plot",
        "description": "The image presents a graph with the x-axis labeled \"Digital input code\" and the y-axis labeled \"Differential linearity e"
      },
      {
        "id": "fig_0039",
        "image_path": "out/dac5578/figures/fig_0039.png",
        "classification": "plot",
        "description": "The image presents a graph with the x-axis labeled \"Digital input code\" and the y-axis labeled \"Differential linearity e"
      },
      {
        "id": "fig_0042",
        "image_path": "out/dac5578/figures/fig_0042.png",
        "classification": "plot",
        "description": "The image presents a graph with two lines, one representing the external reference and the other representing the maximu"
      },
      {
        "id": "fig_0045",
        "image_path": "out/dac5578/figures/fig_0045.png",
        "classification": "plot",
        "description": "The image presents a graph with two lines, one representing the external reference and the other indicating the current "
      },
      {
        "id": "fig_0046",
        "image_path": "out/dac5578/figures/fig_0046.png",
        "classification": "plot",
        "description": "The image presents a graph with two lines, one representing the external reference voltage (V) and the other representin"
      },
      {
        "id": "fig_0047",
        "image_path": "out/dac5578/figures/fig_0047.png",
        "classification": "plot",
        "description": "The image presents a graph with the x-axis labeled \"External Reference\" and the y-axis labeled \"Voltage\". The graph disp"
      },
      {
        "id": "fig_0048",
        "image_path": "out/dac5578/figures/fig_0048.png",
        "classification": "plot",
        "description": "The image presents a line graph that displays the relationship between temperature and voltage in a series of electronic"
      },
      {
        "id": "fig_0049",
        "image_path": "out/dac5578/figures/fig_0049.png",
        "classification": "plot",
        "description": "The image presents a graph with the x-axis labeled \"External Reference\" and the y-axis labeled \"Voltage (V)\", indicating"
      },
      {
        "id": "fig_0052",
        "image_path": "out/dac5578/figures/fig_0052.png",
        "classification": "plot",
        "description": "The image presents a graph that displays the relationship between voltage and current in a circuit, with the x-axis repr"
      },
      {
        "id": "fig_0053",
        "image_path": "out/dac5578/figures/fig_0053.png",
        "classification": "plot",
        "description": "The image presents a graph that displays the relationship between voltage and current in a DC circuit, with the x-axis r"
      },
      {
        "id": "fig_0054",
        "image_path": "out/dac5578/figures/fig_0054.png",
        "classification": "plot",
        "description": "The image presents a graph that displays the relationship between voltage and current in a circuit, with the x-axis repr"
      },
      {
        "id": "fig_0055",
        "image_path": "out/dac5578/figures/fig_0055.png",
        "classification": "plot",
        "description": "The image presents a graph with two lines, one representing the DC current and the other representing the AC voltage. Th"
      },
      {
        "id": "fig_0056",
        "image_path": "out/dac5578/figures/fig_0056.png",
        "classification": "plot",
        "description": "The image presents a graph with two lines, one representing the DC current and the other representing the AC voltage. Th"
      },
      {
        "id": "fig_0057",
        "image_path": "out/dac5578/figures/fig_0057.png",
        "classification": "plot",
        "description": "The image presents a graph with two lines, one representing the DC current and the other representing the AC voltage. Th"
      },
      {
        "id": "fig_0060",
        "image_path": "out/dac5578/figures/fig_0060.png",
        "classification": "plot",
        "description": "The image presents a graph that displays the relationship between power supply current and digital input code for an ele"
      },
      {
        "id": "fig_0061",
        "image_path": "out/dac5578/figures/fig_0061.png",
        "classification": "plot",
        "description": "The image presents a graph that displays the relationship between power supply voltage and current in a circuit. The x-a"
      },
      {
        "id": "fig_0062",
        "image_path": "out/dac5578/figures/fig_0062.png",
        "classification": "plot",
        "description": "The image presents a black and white diagram of a sensor's output, which is displayed in a graph format. The x-axis repr"
      },
      {
        "id": "fig_0063",
        "image_path": "out/dac5578/figures/fig_0063.png",
        "classification": "plot",
        "description": "The image presents a graph that displays the relationship between power supply voltage and current, with the x-axis repr"
      },
      {
        "id": "fig_0064",
        "image_path": "out/dac5578/figures/fig_0064.png",
        "classification": "plot",
        "description": "The image presents a graph that displays the external reference for a 5V power supply current, with the x-axis represent"
      },
      {
        "id": "fig_0068",
        "image_path": "out/dac5578/figures/fig_0068.png",
        "classification": "plot",
        "description": "The image presents a black and white line graph that displays the rise and fall of a signal over time, with the x-axis r"
      },
      {
        "id": "fig_0069",
        "image_path": "out/dac5578/figures/fig_0069.png",
        "classification": "timing_diagram",
        "description": "The image presents a graph of an electrical circuit, with the x-axis representing time and the y-axis indicating voltage"
      },
      {
        "id": "fig_0070",
        "image_path": "out/dac5578/figures/fig_0070.png",
        "classification": "plot",
        "description": "The image presents a graph with two lines on it, each representing the power-on glidech screen of a device. The first li"
      },
      {
        "id": "fig_0071",
        "image_path": "out/dac5578/figures/fig_0071.png",
        "classification": "plot",
        "description": "The image presents a black and white line graph that displays the relationship between two variables, with each variable"
      },
      {
        "id": "fig_0072",
        "image_path": "out/dac5578/figures/fig_0072.png",
        "classification": "plot",
        "description": "The image presents a graph with two lines, one labeled \"2V\" and the other \"2m/s\". The graph is set against a black backg"
      },
      {
        "id": "fig_0076",
        "image_path": "out/dac5578/figures/fig_0076.png",
        "classification": "timing_diagram",
        "description": "The image presents a graph that displays the relationship between voltage and current in a circuit, with time on the x-a"
      },
      {
        "id": "fig_0078",
        "image_path": "out/dac5578/figures/fig_0078.png",
        "classification": "timing_diagram",
        "description": "The image presents a black and white diagram of an electronic device, with the x-axis labeled \"Time (s)\" and the y-axis "
      },
      {
        "id": "fig_0079",
        "image_path": "out/dac5578/figures/fig_0079.png",
        "classification": "plot",
        "description": "The image presents a graph that displays the Glitch Energy of a device, which is measured in 5V and 12bit. The device's "
      },
      {
        "id": "fig_0081",
        "image_path": "out/dac5578/figures/fig_0081.png",
        "classification": "plot",
        "description": "The image presents a black and white diagram of an electronic device, with the x-axis labeled \"Time\" and the y-axis labe"
      },
      {
        "id": "fig_0084",
        "image_path": "out/dac5578/figures/fig_0084.png",
        "classification": "plot",
        "description": "The image presents a graph that displays the relationship between frequency and AC output, with three different lines re"
      },
      {
        "id": "fig_0085",
        "image_path": "out/dac5578/figures/fig_0085.png",
        "classification": "plot",
        "description": "The image presents a black and white diagram of a DC ac output noise measurement, with the x-axis representing time in s"
      },
      {
        "id": "fig_0087",
        "image_path": "out/dac5578/figures/fig_0087.png",
        "classification": "plot",
        "description": "The image presents a graph with two lines, one representing the external reference and the other indicating the current "
      },
      {
        "id": "fig_0088",
        "image_path": "out/dac5578/figures/fig_0088.png",
        "classification": "plot",
        "description": "The image presents a graph that displays the relationship between power supply current and digital input code for an ele"
      },
      {
        "id": "fig_0089",
        "image_path": "out/dac5578/figures/fig_0089.png",
        "classification": "plot",
        "description": "The image presents a line graph that displays the supply current of a particular electronic component over time, with ea"
      },
      {
        "id": "fig_0092",
        "image_path": "out/dac5578/figures/fig_0092.png",
        "classification": "plot",
        "description": "The image presents a graph with the x-axis labeled \"Digital input code\" and the y-axis labeled \"Linear error\". The graph"
      },
      {
        "id": "fig_0093",
        "image_path": "out/dac5578/figures/fig_0093.png",
        "classification": "plot",
        "description": "The image presents a line graph with the x-axis labeled \"Digital input code\" and the y-axis labeled \"Linearity error\". T"
      },
      {
        "id": "fig_0094",
        "image_path": "out/dac5578/figures/fig_0094.png",
        "classification": "plot",
        "description": "The image presents a graph that displays the relationship between digital input code (DAC) and channel numbers, with cha"
      },
      {
        "id": "fig_0095",
        "image_path": "out/dac5578/figures/fig_0095.png",
        "classification": "plot",
        "description": "The image presents a graph with the x-axis labeled \"Digital input code\" and the y-axis labeled \"Differential linearity e"
      },
      {
        "id": "fig_0096",
        "image_path": "out/dac5578/figures/fig_0096.png",
        "classification": "plot",
        "description": "The image presents a graph with the x-axis labeled \"Digital input code\" and the y-axis labeled \"Differential linearity e"
      },
      {
        "id": "fig_0097",
        "image_path": "out/dac5578/figures/fig_0097.png",
        "classification": "plot",
        "description": "The image presents a graph with two lines, one representing the differential linearity error and the other showing the d"
      },
      {
        "id": "fig_0101",
        "image_path": "out/dac5578/figures/fig_0101.png",
        "classification": "plot",
        "description": "The image presents a graph that displays the relationship between digital input code (DAC) and linear error. The graph s"
      },
      {
        "id": "fig_0102",
        "image_path": "out/dac5578/figures/fig_0102.png",
        "classification": "plot",
        "description": "The image presents a graph that displays the relationship between linearity error and digital input code (DAC) for vario"
      },
      {
        "id": "fig_0103",
        "image_path": "out/dac5578/figures/fig_0103.png",
        "classification": "plot",
        "description": "The image presents a graph with the x-axis labeled \"Digital input code\" and the y-axis labeled \"Linearity error\". The gr"
      },
      {
        "id": "fig_0104",
        "image_path": "out/dac5578/figures/fig_0104.png",
        "classification": "plot",
        "description": "The image presents a graph with two lines, one representing the differential linearity error and the other showing the d"
      },
      {
        "id": "fig_0105",
        "image_path": "out/dac5578/figures/fig_0105.png",
        "classification": "plot",
        "description": "The image presents a graph with two lines, one representing the differential linearity error and the other showing the d"
      },
      {
        "id": "fig_0106",
        "image_path": "out/dac5578/figures/fig_0106.png",
        "classification": "plot",
        "description": "The image presents a graph with the x-axis labeled \"Digital input code\" and the y-axis labeled \"Differential linearity e"
      },
      {
        "id": "fig_0108",
        "image_path": "out/dac5578/figures/fig_0108.png",
        "classification": "plot",
        "description": "The image presents a graph with the x-axis labeled \"Digital input code\" and the y-axis labeled \"Linear error\". The graph"
      },
      {
        "id": "fig_0109",
        "image_path": "out/dac5578/figures/fig_0109.png",
        "classification": "plot",
        "description": "The image presents a graph with the x-axis labeled \"Digital input code\" and the y-axis labeled \"Linear error\". The graph"
      },
      {
        "id": "fig_0110",
        "image_path": "out/dac5578/figures/fig_0110.png",
        "classification": "plot",
        "description": "The image presents a graph with the x-axis labeled \"Digital input code\" and the y-axis labeled \"Linear error\". The graph"
      },
      {
        "id": "fig_0111",
        "image_path": "out/dac5578/figures/fig_0111.png",
        "classification": "plot",
        "description": "The image presents a graph with the x-axis labeled \"Digital input code\" and the y-axis labeled \"Differential linearity e"
      },
      {
        "id": "fig_0112",
        "image_path": "out/dac5578/figures/fig_0112.png",
        "classification": "plot",
        "description": "The image presents a graph with the x-axis labeled \"Digital input code\" and the y-axis labeled \"Differential linearity e"
      },
      {
        "id": "fig_0113",
        "image_path": "out/dac5578/figures/fig_0113.png",
        "classification": "plot",
        "description": "The image presents a graph with the x-axis labeled \"Digital input code\" and the y-axis labeled \"Differential linearity e"
      },
      {
        "id": "fig_0116",
        "image_path": "out/dac5578/figures/fig_0116.png",
        "classification": "plot",
        "description": "The image presents a graph with two lines, one representing the linearity error and the other showing the temperature of"
      },
      {
        "id": "fig_0117",
        "image_path": "out/dac5578/figures/fig_0117.png",
        "classification": "plot",
        "description": "The image presents a graph with two lines, one representing the linear error and the other representing the temperature."
      },
      {
        "id": "fig_0118",
        "image_path": "out/dac5578/figures/fig_0118.png",
        "classification": "plot",
        "description": "The image presents a graph with two lines, one representing the error in linearity and the other showing the temperature"
      },
      {
        "id": "fig_0119",
        "image_path": "out/dac5578/figures/fig_0119.png",
        "classification": "plot",
        "description": "The image presents a graph with two lines, one representing the external reference and the other representing the temper"
      },
      {
        "id": "fig_0120",
        "image_path": "out/dac5578/figures/fig_0120.png",
        "classification": "plot",
        "description": "The image presents a graph with two lines, one representing the external reference and the other representing the maximu"
      },
      {
        "id": "fig_0121",
        "image_path": "out/dac5578/figures/fig_0121.png",
        "classification": "plot",
        "description": "The image presents a graph with two lines, one representing the external reference and the other representing the temper"
      },
      {
        "id": "fig_0124",
        "image_path": "out/dac5578/figures/fig_0124.png",
        "classification": "plot",
        "description": "The image presents a graph with two lines, one representing the external reference and the other indicating the current "
      },
      {
        "id": "fig_0125",
        "image_path": "out/dac5578/figures/fig_0125.png",
        "classification": "plot",
        "description": "The image presents a graph that displays the relationship between power supply current and temperature, with two lines o"
      },
      {
        "id": "fig_0126",
        "image_path": "out/dac5578/figures/fig_0126.png",
        "classification": "plot",
        "description": "The image presents a graph with the x-axis labeled \"External Reference\" and the y-axis labeled \"Temperature (°C)\". The g"
      },
      {
        "id": "fig_0127",
        "image_path": "out/dac5578/figures/fig_0127.png",
        "classification": "plot",
        "description": "The image presents a graph with temperature values on the y-axis and time intervals on the x-axis, showing how the tempe"
      },
      {
        "id": "fig_0128",
        "image_path": "out/dac5578/figures/fig_0128.png",
        "classification": "plot",
        "description": "The image presents a graph with temperature values on the y-axis and time intervals on the x-axis, indicating that it is"
      },
      {
        "id": "fig_0131",
        "image_path": "out/dac5578/figures/fig_0131.png",
        "classification": "plot",
        "description": "The image presents a graph that displays the relationship between voltage and current in a DC circuit, specifically focu"
      },
      {
        "id": "fig_0132",
        "image_path": "out/dac5578/figures/fig_0132.png",
        "classification": "plot",
        "description": "The image presents a graph that displays the relationship between the input voltage and current of a DC load, as well as"
      },
      {
        "id": "fig_0133",
        "image_path": "out/dac5578/figures/fig_0133.png",
        "classification": "plot",
        "description": "The image presents a graph that displays the relationship between voltage and current in a DC circuit, with two lines re"
      },
      {
        "id": "fig_0134",
        "image_path": "out/dac5578/figures/fig_0134.png",
        "classification": "plot",
        "description": "The image presents a graph with two lines, one representing the DC load and the other representing the AC load on a circ"
      },
      {
        "id": "fig_0135",
        "image_path": "out/dac5578/figures/fig_0135.png",
        "classification": "plot",
        "description": "The image presents a graph with two lines, one representing the DC load and the other representing the AC load on a circ"
      },
      {
        "id": "fig_0136",
        "image_path": "out/dac5578/figures/fig_0136.png",
        "classification": "plot",
        "description": "The image presents a graph with two lines, one representing the DC current and the other representing the AC voltage. Th"
      },
      {
        "id": "fig_0139",
        "image_path": "out/dac5578/figures/fig_0139.png",
        "classification": "plot",
        "description": "The image presents a graph that displays the power supply of an electronic device, with the x-axis representing time and"
      },
      {
        "id": "fig_0140",
        "image_path": "out/dac5578/figures/fig_0140.png",
        "classification": "plot",
        "description": "The image presents a detailed electronic datasheet for a device that measures the rise and fall of an external reference"
      },
      {
        "id": "fig_0141",
        "image_path": "out/dac5578/figures/fig_0141.png",
        "classification": "plot",
        "description": "The image presents a black and white diagram of a sensor's output, which is displayed in millivolts (mV). The diagram sh"
      },
      {
        "id": "fig_0142",
        "image_path": "out/dac5578/figures/fig_0142.png",
        "classification": "plot",
        "description": "The image presents a graph that displays the power supply current of a device over time, with the x-axis representing ti"
      },
      {
        "id": "fig_0143",
        "image_path": "out/dac5578/figures/fig_0143.png",
        "classification": "plot",
        "description": "The image presents a technical diagram of a falling edge, with the x-axis labeled \"External Reference\" and the y-axis la"
      },
      {
        "id": "fig_0144",
        "image_path": "out/dac5578/figures/fig_0144.png",
        "classification": "plot",
        "description": "The image presents a black and white diagram that illustrates the falling edge of a trigger pulse, with time intervals r"
      },
      {
        "id": "fig_0147",
        "image_path": "out/dac5578/figures/fig_0147.png",
        "classification": "timing_diagram",
        "description": "The image presents a graph of an electrical circuit, with the x-axis labeled \"Time\" and the y-axis labeled \"Voltage (V)\""
      },
      {
        "id": "fig_0148",
        "image_path": "out/dac5578/figures/fig_0148.png",
        "classification": "plot",
        "description": "The image presents a detailed electronic datasheet for a device that measures DC voltage and current. The device is desi"
      },
      {
        "id": "fig_0149",
        "image_path": "out/dac5578/figures/fig_0149.png",
        "classification": "schematic",
        "description": "The image presents a detailed electronic circuit diagram, with various components and their respective values labeled in"
      },
      {
        "id": "fig_0150",
        "image_path": "out/dac5578/figures/fig_0150.png",
        "classification": "plot",
        "description": "The image presents a black and white diagram of an electronic device, with the x-axis labeled \"Time\" and the y-axis labe"
      },
      {
        "id": "fig_0151",
        "image_path": "out/dac5578/figures/fig_0151.png",
        "classification": "timing_diagram",
        "description": "The image presents a black and white diagram of a power-off glitch, which is a type of electrical interference that occu"
      },
      {
        "id": "fig_0154",
        "image_path": "out/dac5578/figures/fig_0154.png",
        "classification": "timing_diagram",
        "description": "The image presents a black and white diagram of an electronic device, with the device's name prominently displayed in th"
      },
      {
        "id": "fig_0155",
        "image_path": "out/dac5578/figures/fig_0155.png",
        "classification": "timing_diagram",
        "description": "The image presents a black and white diagram that illustrates the external reference of a clock feed-through (LDCF) circ"
      },
      {
        "id": "fig_0157",
        "image_path": "out/dac5578/figures/fig_0157.png",
        "classification": "timing_diagram",
        "description": "The image presents a black and white diagram of an electronic device, with the device's functionality labeled in black t"
      },
      {
        "id": "fig_0160",
        "image_path": "out/dac5578/figures/fig_0160.png",
        "classification": "schematic",
        "description": "The image presents a detailed circuit diagram for an amplifier, with the components clearly labeled and organized in a v"
      },
      {
        "id": "fig_0181",
        "image_path": "out/dac5578/figures/fig_0181.png",
        "classification": "schematic",
        "description": "The image presents a black and white circuit diagram that illustrates the components of a digital audio processing syste"
      },
      {
        "id": "fig_0182",
        "image_path": "out/dac5578/figures/fig_0182.png",
        "classification": "pinout",
        "description": "The image presents a detailed black and white diagram of a microcontroller circuit board, specifically focusing on the A"
      },
      {
        "id": "fig_0185",
        "image_path": "out/dac5578/figures/fig_0185.png",
        "classification": "pinout",
        "description": "The image presents a detailed circuit diagram for a microcontroller, specifically a DAC18 controller, with three input p"
      },
      {
        "id": "fig_0203",
        "image_path": "out/dac5578/figures/fig_0203.png",
        "classification": "pinout",
        "description": "The image presents a detailed blueprints of a microcontroller, specifically the pin index area and the seating plane. Th"
      },
      {
        "id": "fig_0205",
        "image_path": "out/dac5578/figures/fig_0205.png",
        "classification": "block_diagram",
        "description": "The image presents a detailed technical drawing of a circuit board, specifically focusing on the land pattern and the so"
      },
      {
        "id": "fig_0207",
        "image_path": "out/dac5578/figures/fig_0207.png",
        "classification": "block_diagram",
        "description": "The image presents a detailed technical drawing of a circuit board, specifically focusing on the soldering paste used in"
      },
      {
        "id": "fig_0209",
        "image_path": "out/dac5578/figures/fig_0209.png",
        "classification": "block_diagram",
        "description": "The image presents a black electronic component, likely a circuit board or integrated circuit, resting on its side again"
      },
      {
        "id": "fig_0211",
        "image_path": "out/dac5578/figures/fig_0211.png",
        "classification": "pinout",
        "description": "The image presents a detailed technical drawing of a pin-sized electronic device, likely a component or part of a larger"
      }
    ],
    "resolved_external": []
  }
}